zmcp/__init__.py
zmcp/_placeholder.py
zmcp-0.1.0.dist-info/METADATA
zmcp-0.1.0.dist-info/WHEEL
zmcp-0.1.0.dist-info/licenses/LICENSE
zmcp-0.1.0.dist-info/RECORD
