Metadata-Version: 2.4
Name: zmcp
Version: 0.1.0
Summary: Full-Stack AI Framework For Building Enterprise AI Applications
Project-URL: Homepage, https://zpkg.ai
Project-URL: Documentation, https://zmcp-python.zpkg.ai
Project-URL: Repository, https://github.com/octallium/zmcp-python
Project-URL: Bug Reports, https://github.com/octallium/zmcp-python/issues
Project-URL: Changelog, https://github.com/octallium/zmcp-python/blob/main/CHANGELOG.md
Author: Octallium Inc
Maintainer: Octallium Inc
License: MIT
License-File: LICENSE
Keywords: agentic,agents,ai,automation,enterprise,framework,infrastructure,llm,orchestration,workflow
Classifier: Development Status :: 2 - Pre-Alpha
Classifier: Intended Audience :: Developers
Classifier: License :: OSI Approved :: MIT License
Classifier: Programming Language :: Python :: 3
Classifier: Programming Language :: Python :: 3.12
Classifier: Programming Language :: Python :: 3.13
Classifier: Topic :: Scientific/Engineering :: Artificial Intelligence
Classifier: Topic :: Software Development :: Libraries :: Python Modules
Classifier: Topic :: System :: Distributed Computing
Requires-Python: >=3.12
Provides-Extra: dev
Requires-Dist: black>=23.0; extra == 'dev'
Requires-Dist: mypy>=1.5; extra == 'dev'
Requires-Dist: pre-commit>=3.0; extra == 'dev'
Requires-Dist: pytest-asyncio>=0.21; extra == 'dev'
Requires-Dist: pytest>=7.0; extra == 'dev'
Requires-Dist: ruff>=0.1; extra == 'dev'
